{
	"name": "PL_salesfileload",
	"properties": {
		"activities": [
			{
				"name": "Get Metadata1",
				"type": "GetMetadata",
				"dependsOn": [],
				"policy": {
					"timeout": "0.12:00:00",
					"retry": 0,
					"retryIntervalInSeconds": 30,
					"secureOutput": false,
					"secureInput": false
				},
				"userProperties": [],
				"typeProperties": {
					"dataset": {
						"referenceName": "LS_salesfilesload",
						"type": "DatasetReference"
					},
					"fieldList": [
						"childItems"
					],
					"storeSettings": {
						"type": "AzureBlobStorageReadSettings",
						"recursive": true,
						"enablePartitionDiscovery": false
					},
					"formatSettings": {
						"type": "DelimitedTextReadSettings"
					}
				}
			},
			{
				"name": "FILTER_salesloadfile",
				"type": "Filter",
				"dependsOn": [
					{
						"activity": "Get Metadata1",
						"dependencyConditions": [
							"Succeeded"
						]
					}
				],
				"userProperties": [],
				"typeProperties": {
					"items": {
						"value": "@activity('Get Metadata1').output.childItems",
						"type": "Expression"
					},
					"condition": {
						"value": "@contains(item().name,'Sales')\n",
						"type": "Expression"
					}
				}
			},
			{
				"name": "cpy_Salesfileload_adls",
				"type": "Copy",
				"dependsOn": [
					{
						"activity": "FILTER_salesloadfile",
						"dependencyConditions": [
							"Succeeded"
						]
					}
				],
				"policy": {
					"timeout": "0.12:00:00",
					"retry": 0,
					"retryIntervalInSeconds": 30,
					"secureOutput": false,
					"secureInput": false
				},
				"userProperties": [],
				"typeProperties": {
					"source": {
						"type": "DelimitedTextSource",
						"storeSettings": {
							"type": "AzureBlobStorageReadSettings",
							"recursive": true,
							"wildcardFileName": {
								"value": "@activity('FILTER_salesloadfile').output.value[0].name",
								"type": "Expression"
							},
							"enablePartitionDiscovery": false
						},
						"formatSettings": {
							"type": "DelimitedTextReadSettings"
						}
					},
					"sink": {
						"type": "ParquetSink",
						"storeSettings": {
							"type": "AzureBlobFSWriteSettings"
						},
						"formatSettings": {
							"type": "ParquetWriteSettings"
						}
					},
					"enableStaging": false,
					"translator": {
						"type": "TabularTranslator",
						"typeConversion": true,
						"typeConversionSettings": {
							"allowDataTruncation": true,
							"treatBooleanAsNumber": false
						}
					}
				},
				"inputs": [
					{
						"referenceName": "LS_Salesfile_load",
						"type": "DatasetReference"
					}
				],
				"outputs": [
					{
						"referenceName": "LS_Salesfileload_adlsgen2",
						"type": "DatasetReference"
					}
				]
			}
		],
		"annotations": [],
		"lastPublishTime": "2026-07-08T08:09:53Z"
	},
	"type": "Microsoft.DataFactory/factories/pipelines"
}